README
setup.cfg
setup.py
ndg/__init__.py
ndg/oauth/__init__.py
ndg/oauth/client/__init__.py
ndg/oauth/client/examples/README
ndg/oauth/client/examples/__init__.py
ndg/oauth/client/examples/bearer_tok/README
ndg/oauth/client/examples/bearer_tok/__init__.py
ndg/oauth/client/examples/bearer_tok/bearer_tok_client_app.ini
ndg/oauth/client/examples/bearer_tok/bearer_tok_client_app_ceda.ini
ndg/oauth/client/examples/bearer_tok/bearer_tok_client_app_serve.py
ndg/oauth/client/examples/bearer_tok/bearer_tok_client_app_serve_ceda.py
ndg/oauth/client/examples/shared_config/README
ndg/oauth/client/examples/shared_config/__init__.py
ndg/oauth/client/examples/shared_config/pki/__init__.py
ndg/oauth/client/examples/shared_config/pki/localhost.crt
ndg/oauth/client/examples/shared_config/pki/localhost.key
ndg/oauth/client/examples/shared_config/pki/ca/08bd99c7.0
ndg/oauth/client/examples/shared_config/pki/ca/3c58f906.0
ndg/oauth/client/examples/shared_config/pki/ca/9df51c42.0
ndg/oauth/client/examples/shared_config/pki/ca/__init__.py
ndg/oauth/client/examples/shared_config/pki/ca/ade0138a.0
ndg/oauth/client/examples/shared_config/pki/ca/ff783690.0
ndg/oauth/client/examples/slcs/README
ndg/oauth/client/examples/slcs/__init__.py
ndg/oauth/client/examples/slcs/slcs_client_app.ini
ndg/oauth/client/examples/slcs/slcs_client_app_serve.py
ndg/oauth/client/lib/__init__.py
ndg/oauth/client/lib/certificate_request.py
ndg/oauth/client/lib/http_get_with_credential.py
ndg/oauth/client/lib/oauth2client.py
ndg/oauth/client/lib/openssl_cert.py
ndg/oauth/client/lib/render/__init__.py
ndg/oauth/client/lib/render/configuration.py
ndg/oauth/client/lib/render/factory.py
ndg/oauth/client/lib/render/genshi_renderer.py
ndg/oauth/client/lib/render/renderer_interface.py
ndg/oauth/client/templates/__init__.py
ndg/oauth/client/templates/base.html
ndg/oauth/client/templates/login_complete.html
ndg/oauth/client/templates/public/__init__.py
ndg/oauth/client/templates/public/layout/CEDA_RightButton60.png
ndg_oauth_client.egg-info/PKG-INFO
ndg_oauth_client.egg-info/SOURCES.txt
ndg_oauth_client.egg-info/dependency_links.txt
ndg_oauth_client.egg-info/not-zip-safe
ndg_oauth_client.egg-info/requires.txt
ndg_oauth_client.egg-info/top_level.txt